stm32isp/stm32isp.py
stm32isp-0.8.1.dist-info/LICENSE
stm32isp-0.8.1.dist-info/METADATA
stm32isp-0.8.1.dist-info/WHEEL
stm32isp-0.8.1.dist-info/entry_points.txt
stm32isp-0.8.1.dist-info/top_level.txt
stm32isp-0.8.1.dist-info/RECORD
