Metadata-Version: 2.1
Name: stm32isp
Version: 0.8.1
Summary: Programming Tool for some STM32 Microcontrollers
Author-email: Stefan Wagner <wagiminator@web.de>
Maintainer-email: Stefan Wagner <wagiminator@web.de>
License: MIT License
Project-URL: Homepage, https://wagiminator.github.io/
Project-URL: Repository, https://github.com/wagiminator/MCU-Flash-Tools
Project-URL: Issues, https://github.com/wagiminator/MCU-Flash-Tools/issues
Keywords: ISP,STM32,STM32C011,STM32F030,STM32G030,STM32L011,microcontroller
Classifier: Development Status :: 4 - Beta
Classifier: Programming Language :: Python :: 3
Classifier: License :: OSI Approved :: MIT License
Classifier: Operating System :: OS Independent
Classifier: Intended Audience :: Developers
Classifier: Topic :: Software Development :: Embedded Systems
Requires-Python: >=3.8
License-File: LICENSE
Requires-Dist: pyserial
